setup.py
urban_physiology_toolkit/__init__.py
urban_physiology_toolkit/workflow.py
urban_physiology_toolkit.egg-info/PKG-INFO
urban_physiology_toolkit.egg-info/SOURCES.txt
urban_physiology_toolkit.egg-info/dependency_links.txt
urban_physiology_toolkit.egg-info/requires.txt
urban_physiology_toolkit.egg-info/top_level.txt