Metadata-Version: 1.1
Name: urban-physiology-toolkit
Version: 0.0.1
Summary: Missing data visualization module for Python.
Home-page: https://github.com/ResidentMario/urban_physiology_toolkit
Author: Aleksey Bilogur
Author-email: aleksey.bilogur@gmail.com
License: UNKNOWN
Download-URL: https://github.com/ResidentMario/urban_physiology_toolkit/tarball/0.0.1
Keywords: data,data analysis,open data,civic data,data science
Platform: UNKNOWN
